aries_cloudcontroller/__init__.py
aries_cloudcontroller/acapy_client.py
aries_cloudcontroller/api_client.py
aries_cloudcontroller/api_response.py
aries_cloudcontroller/configuration.py
aries_cloudcontroller/exceptions.py
aries_cloudcontroller/py.typed
aries_cloudcontroller/rest.py
aries_cloudcontroller/api/__init__.py
aries_cloudcontroller/api/action_menu_api.py
aries_cloudcontroller/api/anon_creds_credential_definitions_api.py
aries_cloudcontroller/api/anon_creds_revocation_api.py
aries_cloudcontroller/api/anon_creds_schemas_api.py
aries_cloudcontroller/api/anon_creds_wallet_upgrade_api.py
aries_cloudcontroller/api/basicmessage_api.py
aries_cloudcontroller/api/connection_api.py
aries_cloudcontroller/api/credential_definition_api.py
aries_cloudcontroller/api/credentials_api.py
aries_cloudcontroller/api/default_api.py
aries_cloudcontroller/api/did_api.py
aries_cloudcontroller/api/did_exchange_api.py
aries_cloudcontroller/api/did_rotate_api.py
aries_cloudcontroller/api/discover_features_api.py
aries_cloudcontroller/api/discover_features_v20_api.py
aries_cloudcontroller/api/endorse_transaction_api.py
aries_cloudcontroller/api/introduction_api.py
aries_cloudcontroller/api/issue_credential_v10_api.py
aries_cloudcontroller/api/issue_credential_v20_api.py
aries_cloudcontroller/api/jsonld_api.py
aries_cloudcontroller/api/ledger_api.py
aries_cloudcontroller/api/mediation_api.py
aries_cloudcontroller/api/multitenancy_api.py
aries_cloudcontroller/api/out_of_band_api.py
aries_cloudcontroller/api/present_proof_v10_api.py
aries_cloudcontroller/api/present_proof_v20_api.py
aries_cloudcontroller/api/resolver_api.py
aries_cloudcontroller/api/revocation_api.py
aries_cloudcontroller/api/schema_api.py
aries_cloudcontroller/api/server_api.py
aries_cloudcontroller/api/settings_api.py
aries_cloudcontroller/api/trustping_api.py
aries_cloudcontroller/api/vc_api.py
aries_cloudcontroller/api/wallet_api.py
aries_cloudcontroller/models/__init__.py
aries_cloudcontroller-1.3.0.post20250526.dist-info/licenses/LICENSE
aries_cloudcontroller-1.3.0.post20250526.dist-info/METADATA
aries_cloudcontroller-1.3.0.post20250526.dist-info/WHEEL
aries_cloudcontroller-1.3.0.post20250526.dist-info/top_level.txt
aries_cloudcontroller-1.3.0.post20250526.dist-info/RECORD
