Metadata-Version: 2.4
Name: aries_cloudcontroller
Version: 1.3.0.post20250526
Summary: A simple python client for controlling an ACA-Py agent
Home-page: https://github.com/didx-xyz/aries-cloudcontroller-python
Classifier: Programming Language :: Python :: 3
Classifier: License :: OSI Approved :: Apache Software License
Classifier: Operating System :: OS Independent
Requires-Python: >=3.9
License-File: LICENSE
Requires-Dist: aiohttp<4.0,>=3.9.4
Requires-Dist: aiohttp_retry~=2.9.1
Requires-Dist: orjson>=3.10.10
Requires-Dist: pydantic<3.0,>=2.6
Requires-Dist: python-dateutil>=2
Requires-Dist: typing-extensions<5.0,>=4
Requires-Dist: urllib3<3,>=2.1
Dynamic: classifier
Dynamic: description
Dynamic: description-content-type
Dynamic: home-page
Dynamic: license-file
Dynamic: requires-dist
Dynamic: requires-python
Dynamic: summary
